[
  {
    "entry_idx": 36,
    "exit_idx": 62,
    "entry_time": "2026-04-06 09:00:00",
    "exit_time": "2026-04-07 11:00:00",
    "direction": "LONG",
    "entry_price": 2150.9,
    "close_price": 2085.01,
    "pnl": -65.89,
    "pnl_pct": -3.0634,
    "r_multiple": -2.04,
    "reason": "SL",
    "candles_held": 26,
    "mode": "B_BOS_OB",
    "ob_strength": 60.723445817986686
  },
  {
    "entry_idx": 65,
    "exit_idx": 73,
    "entry_time": "2026-04-07 14:00:00",
    "exit_time": "2026-04-07 22:00:00",
    "direction": "SHORT",
    "entry_price": 2069.44,
    "close_price": 2166.09,
    "pnl": -96.65,
    "pnl_pct": -4.6702,
    "r_multiple": -3.11,
    "reason": "SL",
    "candles_held": 8,
    "mode": "B_BOS_OB",
    "ob_strength": 65.73404036303279
  },
  {
    "entry_idx": 74,
    "exit_idx": 100,
    "entry_time": "2026-04-07 23:00:00",
    "exit_time": "2026-04-09 01:00:00",
    "direction": "LONG",
    "entry_price": 2240.22,
    "close_price": 2172.05,
    "pnl": -68.17,
    "pnl_pct": -3.043,
    "r_multiple": -2.03,
    "reason": "SL",
    "candles_held": 26,
    "mode": "B_BOS_OB",
    "ob_strength": 61.28049132806698
  },
  {
    "entry_idx": 100,
    "exit_idx": 121,
    "entry_time": "2026-04-09 01:00:00",
    "exit_time": "2026-04-09 22:00:00",
    "direction": "SHORT",
    "entry_price": 2178.91,
    "close_price": 2245.29,
    "pnl": -66.38,
    "pnl_pct": -3.0465,
    "r_multiple": -2.03,
    "reason": "SL",
    "candles_held": 21,
    "mode": "B_BOS_OB",
    "ob_strength": 61.21020345699121
  },
  {
    "entry_idx": 112,
    "exit_idx": 121,
    "entry_time": "2026-04-09 13:00:00",
    "exit_time": "2026-04-09 22:00:00",
    "direction": "SHORT",
    "entry_price": 2165.17,
    "close_price": 2245.29,
    "pnl": -80.12,
    "pnl_pct": -3.7004,
    "r_multiple": -2.47,
    "reason": "SL",
    "candles_held": 9,
    "mode": "B_BOS_OB",
    "ob_strength": 61.21020345699121
  },
  {
    "entry_idx": 115,
    "exit_idx": 163,
    "entry_time": "2026-04-09 16:00:00",
    "exit_time": "2026-04-11 16:00:00",
    "direction": "LONG",
    "entry_price": 2208.27,
    "close_price": 2274.52,
    "pnl": 66.25,
    "pnl_pct": 3.0,
    "r_multiple": 2.0,
    "reason": "TP",
    "candles_held": 48,
    "mode": "B_BOS_OB",
    "ob_strength": 60.70689524414856
  },
  {
    "entry_idx": 121,
    "exit_idx": 163,
    "entry_time": "2026-04-09 22:00:00",
    "exit_time": "2026-04-11 16:00:00",
    "direction": "LONG",
    "entry_price": 2197.95,
    "close_price": 2263.89,
    "pnl": 65.94,
    "pnl_pct": 3.0,
    "r_multiple": 2.0,
    "reason": "TP",
    "candles_held": 42,
    "mode": "B_BOS_OB",
    "ob_strength": 60.70689524414856
  },
  {
    "entry_idx": 130,
    "exit_idx": 137,
    "entry_time": "2026-04-10 07:00:00",
    "exit_time": "2026-04-10 14:00:00",
    "direction": "SHORT",
    "entry_price": 2179.3,
    "close_price": 2245.29,
    "pnl": -65.99,
    "pnl_pct": -3.0281,
    "r_multiple": -2.02,
    "reason": "SL",
    "candles_held": 7,
    "mode": "B_BOS_OB",
    "ob_strength": 61.21020345699121
  },
  {
    "entry_idx": 166,
    "exit_idx": 181,
    "entry_time": "2026-04-11 19:00:00",
    "exit_time": "2026-04-12 10:00:00",
    "direction": "LONG",
    "entry_price": 2316.86,
    "close_price": 2197.48,
    "pnl": -119.38,
    "pnl_pct": -5.1525,
    "r_multiple": -3.44,
    "reason": "SL",
    "candles_held": 15,
    "mode": "B_BOS_OB",
    "ob_strength": 64.6695476250818
  },
  {
    "entry_idx": 207,
    "exit_idx": 214,
    "entry_time": "2026-04-13 12:00:00",
    "exit_time": "2026-04-13 19:00:00",
    "direction": "SHORT",
    "entry_price": 2192.57,
    "close_price": 2256.38,
    "pnl": -63.81,
    "pnl_pct": -2.9103,
    "r_multiple": -1.94,
    "reason": "SL",
    "candles_held": 7,
    "mode": "B_BOS_OB",
    "ob_strength": 63.53656941231126
  },
  {
    "entry_idx": 218,
    "exit_idx": 268,
    "entry_time": "2026-04-13 23:00:00",
    "exit_time": "2026-04-16 01:00:00",
    "direction": "LONG",
    "entry_price": 2369.39,
    "close_price": 2352.38,
    "pnl": -17.01,
    "pnl_pct": -0.7179,
    "r_multiple": -0.48,
    "reason": "TIME",
    "candles_held": 50,
    "mode": "B_BOS_OB",
    "ob_strength": 66.60062253384385
  },
  {
    "entry_idx": 233,
    "exit_idx": 281,
    "entry_time": "2026-04-14 14:00:00",
    "exit_time": "2026-04-16 14:00:00",
    "direction": "LONG",
    "entry_price": 2354.4,
    "close_price": 2291.72,
    "pnl": -62.68,
    "pnl_pct": -2.6622,
    "r_multiple": -1.77,
    "reason": "SL",
    "candles_held": 48,
    "mode": "B_BOS_OB",
    "ob_strength": 66.60062253384385
  },
  {
    "entry_idx": 238,
    "exit_idx": 262,
    "entry_time": "2026-04-14 19:00:00",
    "exit_time": "2026-04-15 19:00:00",
    "direction": "SHORT",
    "entry_price": 2314.64,
    "close_price": 2377.05,
    "pnl": -62.41,
    "pnl_pct": -2.6961,
    "r_multiple": -1.8,
    "reason": "SL",
    "candles_held": 24,
    "mode": "B_BOS_OB",
    "ob_strength": 72.66012866626414
  },
  {
    "entry_idx": 274,
    "exit_idx": 304,
    "entry_time": "2026-04-16 07:00:00",
    "exit_time": "2026-04-17 13:00:00",
    "direction": "SHORT",
    "entry_price": 2341.69,
    "close_price": 2399.64,
    "pnl": -57.95,
    "pnl_pct": -2.4747,
    "r_multiple": -1.65,
    "reason": "SL",
    "candles_held": 30,
    "mode": "B_BOS_OB",
    "ob_strength": 60.329094745213666
  },
  {
    "entry_idx": 404,
    "exit_idx": 416,
    "entry_time": "2026-04-21 17:00:00",
    "exit_time": "2026-04-22 05:00:00",
    "direction": "SHORT",
    "entry_price": 2306.72,
    "close_price": 2394.46,
    "pnl": -87.74,
    "pnl_pct": -3.8036,
    "r_multiple": -2.54,
    "reason": "SL",
    "candles_held": 12,
    "mode": "B_BOS_OB",
    "ob_strength": 63.6861574466355
  },
  {
    "entry_idx": 425,
    "exit_idx": 444,
    "entry_time": "2026-04-22 14:00:00",
    "exit_time": "2026-04-23 09:00:00",
    "direction": "LONG",
    "entry_price": 2404.1,
    "close_price": 2328.96,
    "pnl": -75.14,
    "pnl_pct": -3.1257,
    "r_multiple": -2.08,
    "reason": "SL",
    "candles_held": 19,
    "mode": "B_BOS_OB",
    "ob_strength": 60.10624146728162
  },
  {
    "entry_idx": 438,
    "exit_idx": 488,
    "entry_time": "2026-04-23 03:00:00",
    "exit_time": "2026-04-25 05:00:00",
    "direction": "SHORT",
    "entry_price": 2342.61,
    "close_price": 2316.77,
    "pnl": 25.84,
    "pnl_pct": 1.103,
    "r_multiple": 0.74,
    "reason": "TIME",
    "candles_held": 50,
    "mode": "B_BOS_OB",
    "ob_strength": 74.66808705755004
  }
]